LICENSE.txt
MANIFEST.in
README.md
setup.py
tfd/__init__.py
tfd/dbutil.py
tfd/fasta.py
tfd/go.py
tfd/util.py
tfd.egg-info/PKG-INFO
tfd.egg-info/SOURCES.txt
tfd.egg-info/dependency_links.txt
tfd.egg-info/top_level.txt