Metadata-Version: 1.1
Name: tfd
Version: 0.3.0
Summary: Random modules in a personal namespace.
Home-page: https://github.com/todddeluca/tfd
Author: Todd Francis DeLuca
Author-email: todddeluca@yahoo.com
License: MIT
Keywords: python gene ontology
Platform: UNKNOWN
Classifier: License :: OSI Approved :: MIT License
Classifier: Development Status :: 3 - Alpha
Classifier: Programming Language :: Python :: 2
Classifier: Programming Language :: Python :: 2.7
